<?xml version="1.0"?>
<ScreenText xmlns:xsi="http://www.w3.org/2001/XMLSchema-instance" xmlns:xsd="http://www.w3.org/2001/XMLSchema">
    <CraftUploaded>Craft uploaded!</CraftUploaded>
    <CraftSaved>Craft saved!</CraftSaved>
    <ModFileGenerated>LMPModControl.xml file generated in your KSP folder</ModFileGenerated>
    <Disconected>You have been disconnected!</Disconected>
    <Spectating>This vessel is being controlled by</Spectating>
    <SafetyBubble>Remember!! While you're inside the safety bubble you won't be seen by other players!!</SafetyBubble>
    <CannotRecover>Cannot recover vessel, the vessel is not yours.</CannotRecover>
    <CannotTerminate>Cannot terminate vessel, the vessel is not yours.</CannotTerminate>
    <SpectatingRemoved>The vessel you were spectating was removed</SpectatingRemoved>
    <WarpDisabled>Cannot warp, warping is disabled on this server</WarpDisabled>
    <NotWarpMaster>Cannot warp, you are not the warp master!</NotWarpMaster>
    <WaitingSubspace>Cannot warp, waiting subspace id from the server</WaitingSubspace>
    <ScreenshotInterval>Interval between screenshots is $1 seconds. Cannot upload the screenshot at this moment</ScreenshotInterval>
    <CraftLibraryInterval>Interval between craft library requests is $1 seconds. Cannot process the request at this moment</CraftLibraryInterval>
    <ScreenshotTaken>Screenshot uploaded!</ScreenshotTaken>
    <ImageSaved>Image saved to GameData/LunaMultiplayer/Screenshots</ImageSaved>
    <IncreasedInterpolationOffset>Warning! Your interpolation offset has been increased as it was too low for this server</IncreasedInterpolationOffset>
    <SackingKerbalsNotAllowed>This server does not allow firing kerbals</SackingKerbalsNotAllowed>
    <CannotLoadGames>LMP does not allow loading savegames</CannotLoadGames>
    <KerbalNotYours>Another player is using this kerbal</KerbalNotYours>
</ScreenText>
